bump_ghw/__init__.py
bump_ghw-0.1.0.dist-info/licenses/LICENSE
bump_ghw-0.1.0.dist-info/WHEEL
bump_ghw-0.1.0.dist-info/entry_points.txt
bump_ghw-0.1.0.dist-info/METADATA
bump_ghw-0.1.0.dist-info/RECORD
