Metadata-Version: 2.4
Name: bump-ghw
Version: 0.1.0
Summary: CLI tool to mange your github workflow step versions
Keywords: github,version control,sha,actions
Author: CoderJoshDK
Author-email: CoderJoshDK <74162303+CoderJoshDK@users.noreply.github.com>
License-Expression: MIT
License-File: LICENSE
Classifier: Development Status :: 4 - Beta
Classifier: Programming Language :: Python :: 3
Classifier: Programming Language :: Python :: 3.11
Classifier: Programming Language :: Python :: 3.12
Classifier: Programming Language :: Python :: 3.13
Classifier: Programming Language :: Python :: 3.14
Requires-Dist: githubkit>=0.14.0
Requires-Dist: requests>=2.32.5
Requires-Dist: typer>=0.20.0
Requires-Python: >=3.11
Project-URL: Homepage, https://github.com/CoderJoshDK/bump-ghw
Project-URL: Issues, https://github.com/CoderJoshDK/bump-ghw/issues
Project-URL: Repository, https://github.com/CoderJoshDK/bump-ghw.git
